{
"வகுப்பு": "4 ஆம் வகுப்பு",
"பருவம்": "பருவம் 2",
"பாட_எண்": "குறிப்பிடப்படவில்லை",
"பாட_தலைப்பு": "யானைக்கும் பானைக்கும் சரி",
"பாடக்குறிப்புகள்": {
"முழுமையான_பாட_சுருக்கம்": "மரியாதை இராமன் ஒருமுறை ஒரு விசித்திரமான வழக்கை எதிர்கொண்டார். உழவர் ஒருவர் தன் மகனின் திருமண விழாவில் ஊர்வலம் விடுவதற்காக அரபு வணிகர் ஒருவரிடம் யானையை இரவல் கேட்டார். வணிகரும் யானையைக் கொடுத்தார். ஆனால் ஊர்வலத்தின் போது யானை தற்செயலாக இறந்துவிட்டது. உழவர், இறந்துபோன யானைக்குப் பதிலாக அதன் விலையையோ அல்லது வேறு யானையையோ வாங்கித் தருவதாகக் கூறினார். ஆனால் அரபு வணிகர் அதனை ஏற்றுக்கொள்ள மறுத்து, இறந்துபோன அதே யானைதான் வேண்டும் என்று அடம்பிடித்தார். \n\nஇந்த வழக்கு மரியாதை இராமனிடம் வந்தது. இருவர் தரப்பு நியாயத்தையும் கேட்ட அவர், உழவரை மட்டும் தனியே அழைத்து ஒரு திட்டம் வகுத்துக் கொடுத்தார். உழவரை நீதிமன்றத்திற்கு அழைக்க வணிகரே செல்வார் என்றும், அப்போது வீட்டின் கதவுக்குப் பின்னால் பழைய பானைகளை அடுக்கி வைத்துவிட்டு, கதவைத் தாழ்ப்பாள் போடாமல் மூடி வைக்குமாறும் கூறினார். அதன்படியே உழவரும் செய்தார். ஆத்திரத்துடன் வந்த வணிகர் கதவை வேகமாகத் தள்ள, பின்னாலிருந்த பழைய பானைகள் உடைந்து நொறுங்கின. உடனே உழவர், காலங்காலமாகப் போற்றி வைத்திருந்த தன் பழைய பானைகளை அதே போல் திருப்பித் தர வேண்டும் என்று கூக்குரலிட்டார். \n\nநீதிமன்றத்தில், உழவர் உடைந்த பானைகளைத் திருப்பிக் கேட்டார். மரியாதை இராமன் வணிகரிடம், 'நீங்கள் உடைத்த பானைகளைத் திருப்பித் தந்துவிட்டால், உழவரும் உங்கள் யானையைத் திருப்பித் தந்துவிடுவார்' என்று தீர்ப்பளித்தார். வணிகர் தம்மால் பழைய பானைகளைத் தர முடியாது என மன்னிப்புக் கோரினார். உடனே மரியாதை இராமன், 'உம்மாலேயே திருப்பித் தரமுடியாது என்றால் உழவரால் மட்டும் எப்படித் திருப்பித் தரமுடியும்? ஆதலால் யானைக்கும் பானைக்கும் சரியாகப் போய்விட்டது' எனத் தீர்ப்பளித்தார்.",
"கூடுதல்_பகுதிகள்_மற்றும்_குறிப்புகள்": [
"கதையின் முக்கிய மாந்தர்கள்: மரியாதை இராமன் (நீதிபதி), உழவர், அரபு வணிகர்.",
"பிரச்சனைக்கான காரணம்: இரவலாக வாங்கப்பட்ட யானை தற்செயலாக இறந்தது.",
"உழவரின் இழப்பீடு: யானைக்கு இணையான பணம் அல்லது வேறு யானை தருவதாக உழவர் ஒப்புக்கொண்டார்.",
"வணிகரின் பிடிவாதம்: இறந்துபோன அதே யானைதான் வேண்டும் என்று அடம்பிடித்தார்.",
"மரியாதை இராமனின் தந்திரம்: உடைந்த பழைய பானைகளை வைத்து வணிகரின் பிடிவாதத்தை முறியடித்தார்."
],
"நினைவில்_கொள்க": [
"நீதி: ஆத்திரக்காரனுக்குப் புத்தி மட்டு.",
"விசித்திரமான வழக்கை தீர்த்து வைத்தவர் மரியாதை இராமன்.",
"யானையை இரவல் கொடுத்தவர் அரபு வணிகர்.",
"யானை இரவல் வாங்கப்பட்ட நிகழ்வு: உழவரின் மகன் திருமண ஊர்வலம்."
],
"புத்தக_பின்புற_மதிப்பீட்டு_வினாக்கள்_ஒரு_மதிப்பெண்": {
"கோடிட்ட_இடங்களை_நிரப்புக": [
"1. வணிகர் அரபு நாட்டைச் சேர்ந்தவர்.",
"2. உழவர், வணிகர் இருவரின் வழக்கை எதிர்கொண்டவர் மரியாதை இராமன்.",
"3. திருமண ஊர்வலத்தில் யானை இறந்து விட்டது.",
"4. பழைய பானைகள் கீழே விழுந்து நொறுங்கின."
],
"சொற்களை_முறைப்படுத்தி_சரியான_தொடரமைத்து_எழுதுக": [
"1. ஊர்வலத்தில் யானை தற்செயலாக இறந்துவிட்டது.",
"2. பானைகள் கீழே விழுந்து உடைந்து விட்டன.",
"3. மரியாதை இராமன் விசித்திரமான வழக்கை எதிர்கொண்டார்.",
"4. கதவின் பின்னால் பானைகள் அடுக்கி வைக்கப்பட்டன."
],
"கட்டத்திலிருந்து_விடை_காண்போமா": [
"இடமிருந்து வலம்: 1. பழைமை என்பது இதன் பொருள் - தொன்மை (அல்லது பழைய)",
"இடமிருந்து வலம்: 2. வீட்டின் முகப்பில் உள்ளது - கதவு",
"இடமிருந்து வலம்: 3. தும்பிக்கை உள்ள விலங்கு - யானை",
"மேலிருந்து கீழ்: 2. உடலின் ஓர் உறுப்பு - கண்/கை (கதையின்படி பொருத்தமான சொல்)",
"மேலிருந்து கீழ்: 4. வேளாண் தொழில் செய்பவர் - உழவர்"
]
}
},
"கேள்விகள்": [
{
"கேள்வி": "1. 'யானைக்கும் பானைக்கும் சரி' என்ற கதையில் வழக்கை விசாரித்தவர் யார்?",
"ஆப்ஷன்கள்": ["அரபு வணிகர்", "உழவர்", "மரியாதை இராமன்", "ஊர் தலைவர்"],
"விடை": "மரியாதை இராமன்",
"விளக்கம்": "கதையின் தொடக்கத்திலேயே மரியாதை இராமன் இந்த விசித்திரமான வழக்கை எதிர்கொண்டார் என்று குறிப்பிடப்பட்டுள்ளது."
},
{
"கேள்வி": "2. உழவர் யார் மீது வழக்கு தொடரப்பட்டார்?",
"ஆப்ஷன்கள்": ["அரபு வணிகர் மீது", "அரபு வணிகர் உழவர் மீது", "மரியாதை இராமன் மீது", "ஊர் மக்கள் மீது"],
"விடை": "அரபு வணிகர் உழவர் மீது",
"விளக்கம்": "உழவர் ஒருவரின் மீது, அரபு வணிகர் ஒருவர் தொடுத்த வழக்குதான் இது எனப் பாடப்பகுதி கூறுகிறது."
},
{
"கேள்வி": "3. உழவர் யானையை எதற்காக இரவல் கேட்டார்?",
"ஆப்ஷன்கள்": ["விவசாயம் செய்ய", "பாரம் சுமக்க", "மகன் திருமண ஊர்வலத்திற்காக", "கோவில் திருவிழாவிற்காக"],
"விடை": "மகன் திருமண ஊர்வலத்திற்காக",
"விளக்கம்": "தம் மகன் திருமண விழாவில் ஊர்வலம் விடுவதற்காக உழவர் யானையை இரவல் கேட்டார்."
},
{
"கேள்வி": "4. வணிகர் எந்த நாட்டைச் சேர்ந்தவர்?",
"ஆப்ஷன்கள்": ["சீன நாடு", "அரபு நாடு", "தமிழ்நாடு", "ரோமாபுரி"],
"விடை": "அரபு நாடு",
"விளக்கம்": "புத்தகப் பயிற்சி மற்றும் பாடப்பகுதியில் 'அரபு வணிகர்' என்றே குறிப்பிடப்பட்டுள்ளது."
},
{
"கேள்வி": "5. திருமண ஊர்வலத்தின் போது யானைக்கு என்ன நேர்ந்தது?",
"ஆப்ஷன்கள்": ["ஓடிவிட்டது", "திருடு போனது", "தற்செயலாக இறந்துவிட்டது", "மதம் பிடித்தது"],
"விடை": "தற்செயலாக இறந்துவிட்டது",
"விளக்கம்": "ஊர்வலத்தில் யானை தற்செயலாக இறந்துபோய்விட்டது என்று உழவர் கூறுகிறார்."
},
{
"கேள்வி": "6. யானை இறந்தவுடன் உழவர் வணிகரிடம் என்ன தருவதாகக் கூறினார்?",
"ஆப்ஷன்கள்": ["விலையோ அல்லது வேறு யானையோ", "நிலம்", "பொற்காசுகள்", "எதுவும் தரமுடியாது என்றார்"],
"விடை": "விலையோ அல்லது வேறு யானையோ",
"விளக்கம்": "அதற்குரிய விலையையாவது, மாற்றாக வேறு யானையையாவது வாங்கித் தருகிறேன் என்று உழவர் கூறினார்."
},
{
"கேள்வி": "7. வணிகர் உழவரின் கோரிக்கையை ஏற்றுக்கொண்டாரா?",
"ஆப்ஷன்கள்": ["ஏற்றுக்கொண்டார்", "பாதி மட்டும் ஏற்றுக்கொண்டார்", "ஏற்றுக்கொள்ள மறுத்தார்", "பணம் மட்டும் வாங்கிக்கொண்டார்"],
"விடை": "ஏற்றுக்கொள்ள மறுத்தார்",
"விளக்கம்": "இந்த வணிகர் ஏற்றுக்கொள்ள மறுக்கிறார் என்று உழவர் வருத்தத்துடன் கூறினார்."
},
{
"கேள்வி": "8. வணிகர் எதற்காக அடம்பிடித்தார்?",
"ஆப்ஷன்கள்": ["கூடுதல் பணம் வேண்டும் என்று", "வேறு யானை வேண்டும் என்று", "இறந்துபோன அதே யானைதான் வேண்டும் என்று", "உழவரைத் தண்டிக்க வேண்டும் என்று"],
"விடை": "இறந்துபோன அதே யானைதான் வேண்டும் என்று",
"விளக்கம்": "இறந்துபோன அதே யானைதான் வேண்டுமென வணிகர் அடம்பிடித்தார்."
},
{
"கேள்வி": "9. உழவர் கூறியதிலிருந்து உண்மையை உணர்ந்துகொண்ட மரியாதை இராமன் இருவரையும் எங்கு வரச் சொன்னார்?",
"ஆப்ஷன்கள்": ["காவல் நிலையத்திற்கு", "நீதிமன்றத்திற்கு", "அரண்மனைக்கு", "ஊர் மந்தைக்கு"],
"விடை": "நீதிமன்றத்திற்கு",
"விளக்கம்": "'நீங்கள் இருவரும் நாளை நீதிமன்றத்துக்கு வாருங்கள்' என்று கூறி அனுப்பினார்."
},
{
"கேள்வி": "10. மரியாதை இராமன் யாரை மட்டும் தனியே அழைத்து ஆலோசனை கூறினார்?",
"ஆப்ஷன்கள்": ["வணிகரை", "பார்வையாளரை", "உழவரை", "யாரையும் அழைக்கவில்லை"],
"விடை": "உழவரை",
"விளக்கம்": "பின்னர், உழவரை மட்டும் தனியே அழைத்து ஆலோசனை வழங்கினார்."
},
{
"கேள்வி": "11. உழவரை நீதிமன்றத்திற்கு அழைத்து வர யார் வருவார் என மரியாதை இராமன் கூறினார்?",
"ஆப்ஷன்கள்": ["காவலர்கள்", "அரபு வணிகர்", "மரியாதை இராமனே வருவார்", "ஊர் மக்கள்"],
"விடை": "அரபு வணிகர்",
"விளக்கம்": "உங்களை அழைத்து வருவதற்கு அந்த வணிகரை உங்கள் வீட்டிற்கு அனுப்புகிறேன் என்றார்."
},
{
"கேள்வி": "12. உழவர் தன் வீட்டு கதவிற்குப் பின் எதை அடுக்கி வைக்க வேண்டும் என அறிவுறுத்தப்பட்டது?",
"ஆப்ஷன்கள்": ["மூட்டைகளை", "பழைய பானைகளை", "மரக்கட்டைகளை", "புதிய பானைகளை"],
"விடை": "பழைய பானைகளை",
"விளக்கம்": "கதவிற்குப் பின் பழைய பானைகளை அடுக்கி வைக்கச் சொன்னார்."
},
{
"கேள்வி": "13. கதவை எப்படி வைத்திருக்க வேண்டும் என உழவருக்கு கூறப்பட்டது?",
"ஆப்ஷன்கள்": ["பூட்டி வைக்க வேண்டும்", "தாழ்ப்பாள் போட்டு வைக்க வேண்டும்", "தாழ்ப்பாள் போடாமல் வைத்திருக்க வேண்டும்", "முழுவதுமாக திறந்து வைத்திருக்க வேண்டும்"],
"விடை": "தாழ்ப்பாள் போடாமல் வைத்திருக்க வேண்டும்",
"விளக்கம்": "பழைய பானைகளை அடுக்கி வைத்து, கதவைத் தாழ்ப்பாள் போடாமல் வைத்திருங்கள் என்றார்."
},
{
"கேள்வி": "14. வணிகர் உழவர் வீட்டிற்கு வந்தபோது எவ்வாறு கதவைத் தட்டினார்?",
"ஆப்ஷன்கள்": ["மெதுவாக", "ஆத்திரத்துடன்", "தயக்கத்துடன்", "அன்பாக"],
"விடை": "ஆத்திரத்துடன்",
"விளக்கம்": "அவரை அழைத்து வருவதற்காக வந்த வணிகர், ஆத்திரத்துடன் அவர் வீட்டுக் கதவைத் தட்டினார்."
},
{
"கேள்வி": "15. கதவு வேகமாகத் திறந்துகொண்டதால் என்ன நிகழ்ந்தது?",
"ஆப்ஷன்கள்": ["உழவர் கீழே விழுந்தார்", "கதவு உடைந்தது", "பானைகள் கீழே விழுந்து உடைந்து நொறுங்கின", "வணிகர் அடிபட்டார்"],
"விடை": "பானைகள் கீழே விழுந்து உடைந்து நொறுங்கின",
"விளக்கம்": "கதவின் பின்னால் அடுக்கி வைத்திருந்த பானைகள் ஒவ்வொன்றாகக் கீழே விழுந்து உடைந்து நொறுங்கின."
},
{
"கேள்வி": "16. உடைந்த பானைகள் எப்படிப்பட்டவை என்று உழவர் கூறினார்?",
"ஆப்ஷன்கள்": ["நேற்று வாங்கியவை", "காலங்காலமாகப் போற்றி வைத்திருந்த பழம்பானைகள்", "விலை உயர்ந்த பானைகள்", "தங்கப் பானைகள்"],
"விடை": "காலங்காலமாகப் போற்றி வைத்திருந்த பழம்பானைகள்",
"விளக்கம்": "எங்கள் வீட்டில் காலங்காலமாகப் போற்றி வைத்திருந்த பழம்பானைகள் இவை என்று உழவர் கூக்குரலிட்டார்."
},
{
"கேள்வி": "17. உழவர் வணிகரிடம் எதைத் திருப்பித் தரும்படி கேட்டார்?",
"ஆப்ஷன்கள்": ["பணம்", "புதிய பானைகள்", "இதே பழைய பானைகள்", "யானை"],
"விடை": "இதே பழைய பானைகள்",
"விளக்கம்": "எனக்கு இதே பானைகளைத் திருப்பித் தாருங்கள் என்று உழவர் கேட்டார்."
},
{
"கேள்வி": "18. உழவர் கோபமாகக் கத்தியதைக் கண்ட வணிகரின் நிலை என்ன?",
"ஆப்ஷன்கள்": ["சிரித்தார்", "எதிர்த்து சண்டையிட்டார்", "செய்வதறியாது திகைத்தார்", "அழுதுவிட்டார்"],
"விடை": "செய்வதறியாது திகைத்தார்",
"விளக்கம்": "உழவரின் கூக்குரலைக் கேட்ட வணிகர் செய்வதறியாது திகைத்தார்."
},
{
"கேள்வி": "19. உழவர் வீட்டில் நடந்ததை நீதிமன்றத்தில் கூறியவர் யார்?",
"ஆப்ஷன்கள்": ["உழவர்", "வணிகர்", "பக்கத்து வீட்டுக்காரர்", "காவலாளி"],
"விடை": "வணிகர்",
"விளக்கம்": "உழவரின் வீட்டில் நடந்ததைக் கூறினார் வணிகர் என்று பாடப்பகுதி கூறுகிறது."
},
{
"கேள்வி": "20. 'நீங்கள் உடைத்த பானைகளைத் திருப்பித் தந்துவிட்டால், உழவரும் இறந்துபோன யானையைத் திருப்பித் தந்துவிடுவார்' என்று கூறியவர் யார்?",
"ஆப்ஷன்கள்": ["உழவர்", "மரியாதை இராமன்", "அரசர்", "அமைச்சர்"],
"விடை": "மரியாதை இராமன்",
"விளக்கம்": "மரியாதை இராமன் தான் இந்தத் தீர்ப்பை வழங்கினார்."
},
{
"கேள்வி": "21. தீர்ப்பைக் கேட்ட வணிகர் என்ன கூறினார்?",
"ஆப்ஷன்கள்": ["பானைகளைத் தருகிறேன் என்றார்", "என்னை மன்னித்து விடுங்கள், என்னால் தரமுடியாது என்றார்", "யானை வேண்டாம் என்றார்", "வழக்கை வாபஸ் பெறுவதாகக் கூறினார்"],
"விடை": "என்னை மன்னித்து விடுங்கள், என்னால் தரமுடியாது என்றார்",
"விளக்கம்": "வணிகர், 'ஐயா, என்னை மன்னித்து விடுங்கள். என்னால் பழைய பானைகளைத் தரமுடியாது' என்றார்."
},
{
"கேள்வி": "22. மரியாதை இராமன் இறுதியில் வழங்கிய தீர்ப்பு என்ன?",
"ஆப்ஷன்கள்": ["யானைக்குப் பணம் தரவேண்டும்", "பானைக்குப் பணம் தரவேண்டும்", "யானைக்கும் பானைக்கும் சரியாகப் போய்விட்டது", "இருவருக்கும் சிறைத்தண்டனை"],
"விடை": "யானைக்கும் பானைக்கும் சரியாகப் போய்விட்டது",
"விளக்கம்": "ஆதலால், யானைக்கும் பானைக்கும் சரியாகப் போய்விட்டது என்று தீர்ப்பளித்தார்."
},
{
"கேள்வி": "23. இக்கதை உணர்த்தும் நீதி என்ன?",
"ஆப்ஷன்கள்": ["பொறுத்தார் பூமி ஆள்வார்", "ஆத்திரக்காரனுக்குப் புத்தி மட்டு", "அறிவே ஆயுதம்", "குற்றம் பார்க்கில் சுற்றம் இல்லை"],
"விடை": "ஆத்திரக்காரனுக்குப் புத்தி மட்டு",
"விளக்கம்": "பாடத்தின் இறுதியில் 'நீதி: ஆத்திரக்காரனுக்குப் புத்தி மட்டு' என்று கொடுக்கப்பட்டுள்ளது."
},
{
"கேள்வி": "24. 'தற்செயலாக' - இச்சொல்லின் பொருள் உணர்த்துவது எது?",
"ஆப்ஷன்கள்": ["திட்டமிட்டு", "எதிர்பாராமல்", "கோபமாக", "வேகமாக"],
"விடை": "எதிர்பாராமல்",
"விளக்கம்": "தற்செயலாக என்பது எவ்வித முன் திட்டமுமின்றி எதிர்பாராமல் நடப்பதைக் குறிக்கும்."
},
{
"கேள்வி": "25. 'இரவல்' என்பதன் பொருள் என்ன?",
"ஆப்ஷன்கள்": ["விலைக்கு வாங்குதல்", "நிரந்தரமாகப் பெறுதல்", "திருடுதல்", "திரும்பித் தரும் நிபந்தனையுடன் வாங்குதல்"],
"விடை": "திரும்பித் தரும் நிபந்தனையுடன் வாங்குதல்",
"விளக்கம்": "இரவல் என்பது ஒரு பொருளைப் பயன்படுத்திவிட்டு மீண்டும் திருப்பித் தருவதற்காக வாங்குவதாகும்."
},
{
"கேள்வி": "26. பொருத்துக: \n1. வணிகர் - அ. விசித்திரமான வழக்கு \n2. உழவர் - ஆ. தற்செயலாக இறந்தது \n3. யானை - இ. பழைய பானைகள் \n4. மரியாதை இராமன் - ஈ. அரபு நாடு",
"ஆப்ஷன்கள்": ["1-ஈ, 2-இ, 3-ஆ, 4-அ", "1-அ, 2-ஆ, 3-இ, 4-ஈ", "1-இ, 2-ஈ, 3-அ, 4-ஆ", "1-ஆ, 2-அ, 3-ஈ, 4-இ"],
"விடை": "1-ஈ, 2-இ, 3-ஆ, 4-அ",
"விளக்கம்": "வணிகர் அரபு நாட்டைச் சேர்ந்தவர். உழவர் வீட்டில் பழைய பானைகள் உடைந்தன. யானை தற்செயலாக இறந்தது. மரியாதை இராமன் விசித்திரமான வழக்கை விசாரித்தார்."
},
{
"கேள்வி": "27. கூற்று (A): உழவர் பழைய பானைகளை கதவின் பின்னால் அடுக்கி வைத்தார். \nகாரணம் (R): வணிகர் கதவைத் தள்ளும்போது அவை உடைந்து அவருக்குப் பாடம் புகட்ட வேண்டும் என்பதற்காக.",
"ஆப்ஷன்கள்": ["கூற்று சரி, காரணம் தவறு", "கூற்று தவறு, காரணம் சரி", "கூற்று, காரணம் இரண்டும் சரி", "கூற்று, காரணம் இரண்டும் தவறு"],
"விடை": "கூற்று, காரணம் இரண்டும் சரி",
"விளக்கம்": "மரியாதை இராமனின் அறிவுரைப்படி, வணிகருக்குத் திருப்பித் தர முடியாத பொருளின் அருமையைப் புரிய வைக்கவே உழவர் இவ்வாறு செய்தார்."
},
{
"கேள்வி": "28. ஒப்புமை தருக: \nஉழவர் : பழைய பானைகள் :: அரபு வணிகர் : ?",
"ஆப்ஷன்கள்": ["குதிரை", "யானை", "ஒட்டகம்", "தங்கம்"],
"விடை": "யானை",
"விளக்கம்": "உழவர் இழந்ததாகக் கூறியது பழைய பானைகளை, அரபு வணிகர் இழந்தது யானையை."
},
{
"கேள்வி": "29. 'காலங்காலமாக' - இச்சொல்லின் பொருள் என்ன?",
"ஆப்ஷன்கள்": ["நேற்று", "சிறிது காலமாக", "நீண்ட காலமாக / தொன்றுதொட்டு", "எதிர்காலத்தில்"],
"விடை": "நீண்ட காலமாக / தொன்றுதொட்டு",
"விளக்கம்": "பல தலைமுறைகளாக அல்லது மிக நீண்ட காலமாகப் பாதுகாக்கப்படுவதையே 'காலங்காலமாக' என்று உழவர் கூறுகிறார்."
},
{
"கேள்வி": "30. 'ஆத்திரம்' என்ற சொல்லின் எதிர்ச்சொல் எது?",
"ஆப்ஷன்கள்": ["கோபம்", "சினம்", "பொறுமை", "வேகம்"],
"விடை": "பொறுமை",
"விளக்கம்": "ஆத்திரம் என்பது கோபத்தைக் குறிக்கும், அதன் எதிர்ச்சொல் பொறுமை ஆகும்."
},
{
"கேள்வி": "31. 'யானைக்கும் பானைக்கும் சரி' - இத்தொடர் எதைக் குறிக்கிறது?",
"ஆப்ஷன்கள்": ["யானையும் பானையும் ஒன்று", "இருவரின் பிடிவாதமும் முட்டாள்தனமானது, கணக்கு நேர் செய்யப்பட்டது", "பானையை விட யானை பெரியது", "யானையை பானைக்குள் வைக்கலாம்"],
"விடை": "இருவரின் பிடிவாதமும் முட்டாள்தனமானது, கணக்கு நேர் செய்யப்பட்டது",
"விளக்கம்": "இருவராலும் இழந்த அதே பொருளைத் திருப்பித் தர முடியாது என்பதால் பிரச்சனை சமன் செய்யப்பட்டது என்பதைக் குறிக்கிறது."
},
{
"கேள்வி": "32. சொற்களை முறைப்படுத்துக: \nதற்செயலாக / இறந்துவிட்டது / யானை / ஊர்வலத்தில்",
"ஆப்ஷன்கள்": ["ஊர்வலத்தில் தற்செயலாக யானை இறந்துவிட்டது", "யானை தற்செயலாக ஊர்வலத்தில் இறந்துவிட்டது", "ஊர்வலத்தில் யானை தற்செயலாக இறந்துவிட்டது", "இறந்துவிட்டது தற்செயலாக ஊர்வலத்தில் யானை"],
"விடை": "ஊர்வலத்தில் யானை தற்செயலாக இறந்துவிட்டது",
"விளக்கம்": "பொருத்தமான வாக்கிய அமைப்பு இதுவே ஆகும்."
},
{
"கேள்வி": "33. கட்டத்திலிருந்து விடை காண்க: பழைமை என்பது இதன் பொருள் (3 எழுத்துகள்)",
"ஆப்ஷன்கள்": ["புதிய", "பழசு", "தொன்மை", "அண்மை"],
"விடை": "தொன்மை",
"விளக்கம்": "பழைமை என்ற பொருளைத் தரும் சொல் 'தொன்மை' ஆகும்."
},
{
"கேள்வி": "34. கட்டத்திலிருந்து விடை காண்க: வீட்டின் முகப்பில் உள்ளது",
"ஆப்ஷன்கள்": ["சன்னல்", "கதவு", "மாடி", "சுவர்"],
"விடை": "கதவு",
"விளக்கம்": "வீட்டின் முன்பகுதியில் (முகப்பில்) இருப்பது கதவு."
},
{
"கேள்வி": "35. கட்டத்திலிருந்து விடை காண்க: வேளாண் தொழில் செய்பவர்",
"ஆப்ஷன்கள்": ["வணிகர்", "உழவர்", "தச்சர்", "குயவர்"],
"விடை": "உழவர்",
"விளக்கம்": "வேளாண்மை (விவசாயம்) செய்பவரை உழவர் என்று அழைப்போம்."
},
{
"கேள்வி": "36. கட்டத்திலிருந்து விடை காண்க: தும்பிக்கை உள்ள விலங்கு",
"ஆப்ஷன்கள்": ["சிங்கம்", "புலி", "யானை", "குதிரை"],
"விடை": "யானை",
"விளக்கம்": "தும்பிக்கை கொண்ட விலங்கு யானை ஆகும்."
},
{
"கேள்வி": "37. 'கூக்குரலிட்டார்' - இச்சொல்லைப் பிரித்து எழுதக் கிடைப்பது?",
"ஆப்ஷன்கள்": ["கூ + குரலிட்டார்", "கூக்குரல் + இட்டார்", "கூக்கு + ரலிட்டார்", "கூக் + குரலிட்டார்"],
"விடை": "கூக்குரல் + இட்டார்",
"விளக்கம்": "கூக்குரல் + இட்டார் என்பதே சரியான பிரித்தெழுதுதல் ஆகும்."
},
{
"கேள்வி": "38. சொற்களை முறைப்படுத்துக: விசித்திரமான / எதிர்கொண்டார் / வழக்கை / மரியாதை / இராமன்",
"ஆப்ஷன்கள்": ["மரியாதை இராமன் வழக்கை எதிர்கொண்டார் விசித்திரமான", "விசித்திரமான வழக்கை மரியாதை இராமன் எதிர்கொண்டார்", "மரியாதை இராமன் விசித்திரமான வழக்கை எதிர்கொண்டார்", "வழக்கை விசித்திரமான எதிர்கொண்டார் மரியாதை இராமன்"],
"விடை": "மரியாதை இராமன் விசித்திரமான வழக்கை எதிர்கொண்டார்",
"விளக்கம்": "எழுவாய், செயப்படுபொருள், பயனிலை என்ற வரிசையில் அமைந்த சரியான தொடர்."
},
{
"கேள்வி": "39. மரியாதை இராமன் உழவரை மட்டும் ஏன் தனியே அழைத்தார்?",
"ஆப்ஷன்கள்": ["பரிசு கொடுக்க", "ரகசியமாகத் திட்டம் தீட்ட", "தண்டனை வழங்க", "பணம் கேட்க"],
"விடை": "ரகசியமாகத் திட்டம் தீட்ட",
"விளக்கம்": "வணிகருக்குப் பாடம் புகட்ட ஒரு திட்டத்தை ரகசியமாகக் கூறவே தனியே அழைத்தார்."
},
{
"கேள்வி": "40. 'செய்வதறியாது திகைத்தார் வணிகர்' - வணிகர் ஏன் திகைத்தார்?",
"ஆப்ஷன்கள்": ["யானை இறந்ததால்", "உழவர் கோபமாகக் கத்தியதைக் கண்டு", "நீதிபதி கோபப்பட்டதால்", "பானை விலை உயர்ந்தது என்பதால்"],
"விடை": "உழவர் கோபமாகக் கத்தியதைக் கண்டு",
"விளக்கம்": "தற்செயலாகத் தான் உடைத்த பழைய பானைகளுக்காக உழவர் சத்தமிட்டு சண்டையிட்டதைக் கண்டு திகைத்தார்."
},
{
"கேள்வி": "41. கூற்று (A): வணிகர் இறந்துபோன அதே யானையைத் திருப்பித் தரும்படி கேட்டார். \nகாரணம் (R): வணிகருக்கு மாற்று யானை வாங்கும் அளவுக்குப் பணம் இல்லை.",
"ஆப்ஷன்கள்": ["கூற்று சரி, காரணம் சரி", "கூற்று தவறு, காரணம் சரி", "கூற்று சரி, காரணம் தவறு", "இரண்டும் தவறு"],
"விடை": "கூற்று சரி, காரணம் தவறு",
"விளக்கம்": "வணிகர் அதே யானையைக் கேட்டார் என்பது சரி, ஆனால் அதற்கு காரணம் அவரிடம் பணம் இல்லை என்பது அல்ல, அவரது பிடிவாத குணமே காரணம்."
},
{
"கேள்வி": "42. 'விசித்திரமான' என்ற சொல்லுக்கு இணையான பொருள் எது?",
"ஆப்ஷன்கள்": ["சாதாரணமான", "பழக்கமான", "புதுமையான/வினோதமான", "எளிமையான"],
"விடை": "புதுமையான/வினோதமான",
"விளக்கம்": "வழக்கத்திற்கு மாறான ஒன்றை விசித்திரம் (வினோதம்) என்று கூறுவோம்."
},
{
"கேள்வி": "43. 'உம்மாலேயே திருப்பித் தரமுடியாது என்றால் உழவரால் மட்டும் எப்படித் திருப்பித் தரமுடியும்?' என்று மரியாதை இராமன் கேட்டதன் உள்நோக்கம் என்ன?",
"ஆப்ஷன்கள்": ["உழவரைத் தண்டிப்பது", "வணிகரின் தவறை அவருக்குப் புரிய வைப்பது", "பானையின் விலையைக் குறைப்பது", "யானையின் மதிப்பை உயர்த்துவது"],
"விடை": "வணிகரின் தவறை அவருக்குப் புரிய வைப்பது",
"விளக்கம்": "இறந்ததை/உடைந்ததை மீட்க முடியாது என்ற இயற்கை விதியை வணிகர் உணரும்படி செய்யவே இப்படிக் கேட்டார்."
},
{
"கேள்வி": "44. பழைய பானைகள் எவ்வாறு உடைந்தன?",
"ஆப்ஷன்கள்": ["உழவர் உடைத்தார்", "யானை மிதித்தது", "கதவு வேகமாகத் திறந்ததால் கீழே விழுந்து உடைந்தன", "நீதிபதி உடைக்கச் சொன்னார்"],
"விடை": "கதவு வேகமாகத் திறந்ததால் கீழே விழுந்து உடைந்தன",
"விளக்கம்": "வணிகர் ஆத்திரத்துடன் கதவைத் தட்டியபோது கதவு வேகமாகத் திறந்து பானைகள் உடைந்தன."
},
{
"கேள்வி": "45. சொல்லிப் பழகுவோம் பகுதியில் இடம்பெற்றுள்ள தொடர் எது?",
"ஆப்ஷன்கள்": ["யானைக்கும் பானைக்கும் சரி", "பட்டம் விட்ட பட்டாபி, பெட்டிக் கடையில் பொட்டலம் போட்டான்", "ஆத்திரக்காரனுக்குப் புத்தி மட்டு", "தற்செயலாக இறந்தது"],
"விடை": "பட்டம் விட்ட பட்டாபி, பெட்டிக் கடையில் பொட்டலம் போட்டான்",
"விளக்கம்": "நா நெகிழ் பயிற்சிக்காக புத்தகத்தில் கொடுக்கப்பட்ட தொடர் இதுவாகும்."
},
{
"கேள்வி": "46. வாழ்க்கைச் சூழல் வினா: உன் நண்பன் உன்னைத் தவறாகப் புரிந்துகொண்டு உன்மீது சினம் கொண்டால் நீ என்ன செய்வாய்?",
"ஆப்ஷன்கள்": ["நானும் கோபப்படுவேன்", "பேசுவதை நிறுத்திவிடுவேன்", "பொறுமையாக எடுத்துக்கூறி புரிய வைப்பேன்", "சண்டையிடுவேன்"],
"விடை": "பொறுமையாக எடுத்துக்கூறி புரிய வைப்பேன்",
"விளக்கம்": "ஆத்திரப்படாமல் பொறுமையாக உண்மையை உணர்த்துவதே சிறந்த நட்பு மற்றும் செயலாகும்."
},
{
"கேள்வி": "47. இக்கதையில் உழவரின் பண்பு எத்தகையது?",
"ஆப்ஷன்கள்": ["பிடிவாதக்காரர்", "பொறுப்பானவர் மற்றும் நேர்மையானவர்", "கோபக்காரர்", "ஏமாற்றுக்காரர்"],
"விடை": "பொறுப்பானவர் மற்றும் நேர்மையானவர்",
"விளக்கம்": "யானை இறந்தவுடன் மாற்று யானை அல்லது பணம் தருகிறேன் என்று பொறுப்புடன் கூறியதால் அவர் நேர்மையானவர்."
},
{
"கேள்வி": "48. பானைகள் உடைந்தவுடன் உழவர் ஏன் கோபப்படுவது போல் நடித்தார்?",
"ஆப்ஷன்கள்": ["அவருக்குப் பானைகள் மிகவும் பிடிக்கும்", "நீதிபதியின் திட்டத்தை நிறைவேற்ற", "வணிகரிடம் பணம் பறிக்க", "பானைகள் விலை உயர்ந்தவை என்பதால்"],
"விடை": "நீதிபதியின் திட்டத்தை நிறைவேற்ற",
"விளக்கம்": "மரியாதை இராமன் கூறிய திட்டத்தின்படியே உழவர் அவ்வாறு நடித்தார்."
},
{
"கேள்வி": "49. மரியாதை இராமனின் தீர்ப்பு எதன் அடிப்படையில் அமைந்திருந்தது?",
"ஆப்ஷன்கள்": ["பணத்தின் அடிப்படையில்", "உடல் வலிமை அடிப்படையில்", "அறிவுக்கூர்மை மற்றும் நியாயத்தின் அடிப்படையில்", "பதவியின் அடிப்படையில்"],
"விடை": "அறிவுக்கூர்மை மற்றும் நியாயத்தின் அடிப்படையில்",
"விளக்கம்": "ஒருவர் செய்த பிடிவாதத்தை, அதே போன்ற ஒரு சூழலை உருவாக்கி நியாயமான முறையில் முறியடித்தார்."
},
{
"கேள்வி": "50. 'ஆத்திரக்காரனுக்குப் புத்தி மட்டு' என்ற பழமொழியில் 'மட்டு' என்பதன் பொருள் என்ன?",
"ஆப்ஷன்கள்": ["அதிகம்", "குறைவு/எல்லை", "வேகம்", "சிறப்பு"],
"விடை": "குறைவு/எல்லை",
"விளக்கம்": "மட்டு என்பதற்கு அளவு அல்லது குறைவு என்று பொருள். கோபப்படும் போது சிந்திக்கும் திறன் குறையும் என்பதே இதன் அர்த்தம்."
}
]
}